poetry_demo_plugin/__init__.py
poetry_demo_plugin/custom_command.py
poetry_demo_plugin/plugin.py
poetry_demo_plugin-0.0.1.dist-info/METADATA
poetry_demo_plugin-0.0.1.dist-info/WHEEL
poetry_demo_plugin-0.0.1.dist-info/entry_points.txt
poetry_demo_plugin-0.0.1.dist-info/RECORD
