Metadata-Version: 2.1
Name: poetry-demo-plugin
Version: 0.0.1
Summary: Poetry plugin that updates dependencies and bumps their versions in pyproject.toml file
Author: Mousa Zeid Baker
Requires-Python: >=3.9,<4.0
Classifier: Programming Language :: Python :: 3
Classifier: Programming Language :: Python :: 3.9
Classifier: Programming Language :: Python :: 3.10
Classifier: Programming Language :: Python :: 3.11
Classifier: Programming Language :: Python :: 3.12
Classifier: Programming Language :: Python :: 3.13
Requires-Dist: poetry (>=1.8.4,<2.0.0)
